reinautils/__init__.py
reinautils/_modidx.py
reinautils/parameters.py
reinautils/torchutils.py
reinautils-0.0.3.dist-info/LICENSE
reinautils-0.0.3.dist-info/METADATA
reinautils-0.0.3.dist-info/WHEEL
reinautils-0.0.3.dist-info/entry_points.txt
reinautils-0.0.3.dist-info/top_level.txt
reinautils-0.0.3.dist-info/RECORD
